{
  "fetchedAt": "2026-05-25T05:57:24.747Z",
  "indices": [
    {
      "id": "i-nifty",
      "ticker": "^NSEI",
      "current": 23976.15,
      "trend": {
        "d1": 1.08,
        "d5": 1.38,
        "m1": -0.31,
        "spark": [
          23643.5,
          23649.95,
          23618,
          23659,
          23654.7,
          23719.3,
          23976.15
        ]
      }
    },
    {
      "id": "i-sensex",
      "ticker": "^BSESN",
      "current": 76337.85,
      "trend": {
        "d1": 1.22,
        "d5": 1.36,
        "m1": -1.56,
        "spark": [
          75237.99,
          75315.04,
          75200.85,
          75318.39,
          75183.36,
          75415.35,
          76337.85
        ]
      }
    },
    {
      "id": "i-niftym",
      "ticker": "^NSEMDCP50",
      "current": 17634.1,
      "trend": {
        "d1": 0.89,
        "d5": 2.16,
        "m1": 7.18,
        "spark": [
          17273.15,
          17261.35,
          17413.75,
          17499.8,
          17454.1,
          17478.25,
          17634.1
        ]
      }
    },
    {
      "id": "i-spx",
      "ticker": "^GSPC",
      "current": 7473.47,
      "trend": {
        "d1": 0.37,
        "d5": 0.88,
        "m1": 9.63,
        "spark": [
          7501.24,
          7408.5,
          7403.05,
          7353.61,
          7432.97,
          7445.72,
          7473.47
        ]
      }
    },
    {
      "id": "i-nasdaq",
      "ticker": "^IXIC",
      "current": 26343.97,
      "trend": {
        "d1": 0.19,
        "d5": 0.45,
        "m1": 15.02,
        "spark": [
          26635.22,
          26225.14,
          26090.73,
          25870.71,
          26270.36,
          26293.1,
          26343.97
        ]
      }
    },
    {
      "id": "i-vix",
      "ticker": "^INDIAVIX",
      "current": 16.83,
      "trend": {
        "d1": -6,
        "d5": -14.24,
        "m1": -10.69,
        "spark": [
          18.79,
          19.63,
          18.68,
          18.44,
          17.82,
          17.91,
          16.83
        ]
      }
    }
  ],
  "currencies": [
    {
      "id": "fx-usdinr",
      "ticker": "USDINR=X",
      "current": 95.2,
      "trend": {
        "d1": -1.02,
        "d5": -0.81,
        "m1": 2.95,
        "spark": [
          95.71,
          95.97,
          96.27,
          96.57,
          96.53,
          96.17,
          95.2
        ]
      }
    },
    {
      "id": "fx-eurinr",
      "ticker": "EURINR=X",
      "current": 110.8,
      "trend": {
        "d1": -0.8,
        "d5": -0.51,
        "m1": 2.56,
        "spark": [
          111.6,
          111.36,
          112.23,
          111.99,
          112.49,
          111.69,
          110.8
        ]
      }
    },
    {
      "id": "fx-jpyinr",
      "ticker": "JPYINR=X",
      "current": 0.6,
      "trend": {
        "d1": -0.93,
        "d5": -0.74,
        "m1": 3.14,
        "spark": [
          0.6,
          0.6,
          0.61,
          0.61,
          0.61,
          0.6,
          0.6
        ]
      }
    },
    {
      "id": "fx-dxy",
      "ticker": "DX-Y.NYB",
      "current": 98.99,
      "trend": {
        "d1": -0.33,
        "d5": 0.02,
        "m1": 0.34,
        "spark": [
          99.27,
          98.97,
          99.3,
          99.11,
          99.19,
          99.32,
          98.99
        ]
      }
    }
  ],
  "commodities": [
    {
      "id": "c-brent",
      "ticker": "BZ=F",
      "current": 100.21,
      "trend": {
        "d1": -3.22,
        "d5": -10.61,
        "m1": 5.26,
        "spark": [
          109.26,
          112.1,
          111.28,
          105.02,
          102.58,
          103.54,
          100.21
        ]
      }
    },
    {
      "id": "c-gold",
      "ticker": "GC=F",
      "current": 4523.2,
      "trend": {
        "d1": 0.05,
        "d5": -0.64,
        "m1": -5.01,
        "spark": [
          4555.8,
          4552.5,
          4506.3,
          4531.3,
          4539.8,
          4521,
          4523.2
        ]
      }
    },
    {
      "id": "c-steel",
      "ticker": "HRC=F",
      "current": 1155,
      "trend": {
        "d1": 6.94,
        "d5": 6.94,
        "m1": 10.42,
        "spark": [
          1079,
          1080,
          1080,
          1080,
          1080,
          1080,
          1155
        ]
      }
    },
    {
      "id": "c-alum",
      "ticker": "ALI=F",
      "current": 3628.5,
      "trend": {
        "d1": -8.45,
        "d5": -5.75,
        "m1": 5.79,
        "spark": [
          3791.5,
          3850,
          3874,
          3910.75,
          3941,
          3963.5,
          3628.5
        ]
      }
    },
    {
      "id": "c-copper",
      "ticker": "HG=F",
      "current": 6.38,
      "trend": {
        "d1": 0.58,
        "d5": 1.71,
        "m1": 8.66,
        "spark": [
          6.25,
          6.27,
          6.16,
          6.29,
          6.26,
          6.34,
          6.38
        ]
      }
    },
    {
      "id": "c-sugar",
      "ticker": "SB=F",
      "current": 14.7,
      "trend": {
        "d1": -1.34,
        "d5": -0.68,
        "m1": 6.91,
        "spark": [
          14.99,
          14.8,
          14.73,
          15.01,
          14.73,
          14.9,
          14.7
        ]
      }
    }
  ],
  "holdings": [
    {
      "id": "p-infy",
      "ticker": "INFY.NS",
      "current": 1178,
      "trend": {
        "d1": 0.3,
        "d5": 3.11,
        "m1": -8.86,
        "spark": [
          1119,
          1142.5,
          1196.9,
          1193.7,
          1181.2,
          1174.5,
          1178
        ]
      }
    },
    {
      "id": "p-mm",
      "ticker": "M&M.NS",
      "current": 3148.7,
      "trend": {
        "d1": 2.19,
        "d5": 2.11,
        "m1": -3.41,
        "spark": [
          3123.1,
          3083.7,
          3092.3,
          3122.2,
          3099,
          3081.3,
          3148.7
        ]
      }
    },
    {
      "id": "p-hdfcb",
      "ticker": "HDFCBANK.NS",
      "current": 784.65,
      "trend": {
        "d1": 2.33,
        "d5": 2.08,
        "m1": -3.17,
        "spark": [
          767.5,
          768.65,
          762.45,
          759.5,
          759.15,
          766.8,
          784.65
        ]
      }
    },
    {
      "id": "p-asianp",
      "ticker": "ASIANPAINT.NS",
      "current": 2666,
      "trend": {
        "d1": 0.99,
        "d5": 1.99,
        "m1": 12.93,
        "spark": [
          2605.6,
          2614,
          2600.7,
          2598.6,
          2598.8,
          2639.8,
          2666
        ]
      }
    },
    {
      "id": "p-tcs",
      "ticker": "TCS.NS",
      "current": 2310.1,
      "trend": {
        "d1": -0.31,
        "d5": 1.18,
        "m1": -8.49,
        "spark": [
          2264,
          2283.2,
          2327.1,
          2327.4,
          2327.2,
          2317.3,
          2310.1
        ]
      }
    },
    {
      "id": "p-relian",
      "ticker": "RELIANCE.NS",
      "current": 1361,
      "trend": {
        "d1": 0.48,
        "d5": 1.88,
        "m1": 0.8,
        "spark": [
          1336.4,
          1335.9,
          1322.7,
          1359.7,
          1349.6,
          1354.5,
          1361
        ]
      }
    },
    {
      "id": "p-titan",
      "ticker": "TITAN.NS",
      "current": 4154,
      "trend": {
        "d1": 1.82,
        "d5": -0.38,
        "m1": -7.79,
        "spark": [
          4169.1,
          4169.7,
          4102,
          4106.4,
          4083.1,
          4079.8,
          4154
        ]
      }
    },
    {
      "id": "p-bajfin",
      "ticker": "BAJFINANCE.NS",
      "current": 935.25,
      "trend": {
        "d1": 2.04,
        "d5": 1.54,
        "m1": 1.16,
        "spark": [
          910.45,
          921.1,
          923.55,
          923.1,
          907.65,
          916.55,
          935.25
        ]
      }
    },
    {
      "id": "w-pidil",
      "ticker": "PIDILITIND.NS",
      "current": 1486.4,
      "trend": {
        "d1": 0.54,
        "d5": 2.5,
        "m1": 9.53,
        "spark": [
          1467.7,
          1450.2,
          1455.8,
          1455.6,
          1472.8,
          1478.4,
          1486.4
        ]
      }
    },
    {
      "id": "w-dmart",
      "ticker": "DMART.NS",
      "current": 4111,
      "trend": {
        "d1": -0.15,
        "d5": -4.5,
        "m1": -6.58,
        "spark": [
          4358.7,
          4304.7,
          4236,
          4144.2,
          4137.2,
          4117,
          4111
        ]
      }
    },
    {
      "id": "w-divis",
      "ticker": "DIVISLAB.NS",
      "current": 6851,
      "trend": {
        "d1": -0.52,
        "d5": 0.23,
        "m1": 12.01,
        "spark": [
          6760.5,
          6835,
          6912,
          6893,
          6858,
          6887,
          6851
        ]
      }
    },
    {
      "id": "w-pi",
      "ticker": "PIIND.NS",
      "current": 2823.1,
      "trend": {
        "d1": 1.51,
        "d5": -8.82,
        "m1": -4.37,
        "spark": [
          3114.9,
          3096.3,
          3124.6,
          2901.2,
          2740.5,
          2781,
          2823.1
        ]
      }
    }
  ]
}
